pyhk3/__init__.py
pyhk3/add.py
pyhk3/cache.py
pyhk3/cli.py
pyhk3/create.py
pyhk3/defaults.py
pyhk3/dns.py
pyhk3/do.py
pyhk3/hapi.py
pyhk3/ssh.py
pyhk3/tools.py
pyhk3/assets/create_templ.py
pyhk3/assets/hk3s.yml
pyhk3/assets/hk3s_post_create.yml
pyhk3-0.1.0.dist-info/METADATA
pyhk3-0.1.0.dist-info/WHEEL
pyhk3-0.1.0.dist-info/entry_points.txt
pyhk3-0.1.0.dist-info/licenses/LICENSE
pyhk3-0.1.0.dist-info/RECORD
